chucknorris_cli/__init__.py
chucknorris_cli/main.py
chucknorris_cli/quips.py
chucknorris_cli-1.0.0.dist-info/METADATA
chucknorris_cli-1.0.0.dist-info/WHEEL
chucknorris_cli-1.0.0.dist-info/entry_points.txt
chucknorris_cli-1.0.0.dist-info/top_level.txt
chucknorris_cli-1.0.0.dist-info/RECORD
