Metadata-Version: 2.1
Name: chucknorris-cli
Version: 1.0.0
Summary: The finest selection of Chuck Norris jokes.
Home-page: https://github.com/newswangerd/chucknorris-cli
License: UNKNOWN
Platform: UNKNOWN
